mcp_prompt_mapper/__init__.py
mcp_prompt_mapper/main.py
mcp_prompt_mapper-0.1.0.dist-info/METADATA
mcp_prompt_mapper-0.1.0.dist-info/WHEEL
mcp_prompt_mapper-0.1.0.dist-info/top_level.txt
mcp_prompt_mapper-0.1.0.dist-info/RECORD
